minecraft_skin_converter/__init__.py
Minecraft_Skin_Converter-1.2.dist-info/LICENSE
Minecraft_Skin_Converter-1.2.dist-info/METADATA
Minecraft_Skin_Converter-1.2.dist-info/WHEEL
Minecraft_Skin_Converter-1.2.dist-info/top_level.txt
Minecraft_Skin_Converter-1.2.dist-info/RECORD
