Metadata-Version: 2.1
Name: Minecraft-Skin-Converter
Version: 1.2
Summary: Convert minecraft skins from steve to alex and vice versa
Home-page: https://github.com/skillor/minecraft-skin-converter
Author: skillor
Author-email: skillor@gmx.net
License: MIT
Keywords: minecraft,skin-converter,minecraft_skin_converter,minecraft-skin-converter
Platform: UNKNOWN
Classifier: Programming Language :: Python :: 3 :: Only
Classifier: Topic :: Multimedia :: Graphics
Requires-Python: >=3
License-File: LICENSE
Requires-Dist: opencv-python (~=4.5.5.64)
Requires-Dist: numpy (~=1.22.3)
